simple_reload.py
simple_reload-0.1.0.dist-info/METADATA
simple_reload-0.1.0.dist-info/WHEEL
simple_reload-0.1.0.dist-info/licenses/LICENSE
simple_reload-0.1.0.dist-info/RECORD
