Metadata-Version: 2.4
Name: simple-reload
Version: 0.1.0
Summary: Simple library to automatically restart Python scripts on source changes
Project-URL: Homepage, https://github.com/MatthewScholefield/simple-reload
Author-email: "Matthew D. Scholefield" <matthew331199@gmail.com>
License: MIT
License-File: LICENSE
Classifier: Development Status :: 3 - Alpha
Classifier: Intended Audience :: Developers
Classifier: Programming Language :: Python :: 3
Classifier: Programming Language :: Python :: 3.10
Classifier: Programming Language :: Python :: 3.11
Classifier: Programming Language :: Python :: 3.12
Requires-Python: >=3.10
Requires-Dist: watchfiles>=1.0.4
